pyqt_vbounding_box/__init__.py
pyqt_vbounding_box/item.py
pyqt_vbounding_box/vBoundingBox.py
pyqt_vbounding_box-0.0.11.dist-info/LICENSE
pyqt_vbounding_box-0.0.11.dist-info/METADATA
pyqt_vbounding_box-0.0.11.dist-info/WHEEL
pyqt_vbounding_box-0.0.11.dist-info/top_level.txt
pyqt_vbounding_box-0.0.11.dist-info/RECORD
