Metadata-Version: 2.1
Name: pyqt-vbounding-box
Version: 0.0.11
Summary: PyQt QGraphicsView with bounding box. User can move horizontal border of the box vertically.
Home-page: https://github.com/yjg30737/pyqt-vbounding-box.git
Author: Jung Gyu Yoon
Author-email: yjg30737@gmail.com
License: MIT
Platform: UNKNOWN
License-File: LICENSE
Requires-Dist: PyQt5 (>=5.8)
